cloudshell/__init__.py
cloudshell/orch/__init__.py
cloudshell/orch/pool/__init__.py
cloudshell/orch/pool/setup_orchestrator.py
cloudshell/orch/pool/teardown_orchestrator.py
cloudshell/orch/pool/helpers/__init__.py
cloudshell/orch/pool/helpers/consts.py
cloudshell/orch/pool/helpers/email_helper.py
cloudshell/orch/pool/helpers/master_sandbox.py
cloudshell/orch/pool/helpers/utils.py
cloudshell/orch/pool/logic/__init__.py
cloudshell/orch/pool/logic/custom.py
cloudshell/orch/pool/logic/delete.py
cloudshell/orch/pool/logic/new_vm_request.py
cloudshell/orch/pool/logic/power.py
cloudshell/orch/pool/logic/trigger.py
test/__init__.py
test/test_master_sandbox_helpers.py
cloudshell_orch_pool-1.10.0.dist-info/METADATA
cloudshell_orch_pool-1.10.0.dist-info/WHEEL
cloudshell_orch_pool-1.10.0.dist-info/top_level.txt
cloudshell_orch_pool-1.10.0.dist-info/RECORD
